cogmem/__init__.py
cogmem/json_utils.py
cogent_mem-0.0.1.dist-info/LICENSE
cogent_mem-0.0.1.dist-info/METADATA
cogent_mem-0.0.1.dist-info/WHEEL
cogent_mem-0.0.1.dist-info/RECORD
