Metadata-Version: 2.3
Name: cogent-mem
Version: 0.0.1
Summary: An agentic memory driven by cognitive computational models
Author: xmingc
Author-email: chenxm35@gmail.com
Requires-Python: >=3.8,<4.0
Classifier: Programming Language :: Python :: 3
Classifier: Programming Language :: Python :: 3.8
Classifier: Programming Language :: Python :: 3.9
Classifier: Programming Language :: Python :: 3.10
Classifier: Programming Language :: Python :: 3.11
Classifier: Programming Language :: Python :: 3.12
Classifier: Programming Language :: Python :: 3.13
